README.txt
setup.cfg
setup.py
docs/HISTORY.txt
rbco/__init__.py
rbco.rename.egg-info/PKG-INFO
rbco.rename.egg-info/SOURCES.txt
rbco.rename.egg-info/dependency_links.txt
rbco.rename.egg-info/entry_points.txt
rbco.rename.egg-info/namespace_packages.txt
rbco.rename.egg-info/not-zip-safe
rbco.rename.egg-info/requires.txt
rbco.rename.egg-info/top_level.txt
rbco/rename/__init__.py
rbco/rename/console.py
rbco/rename/renaming.py