Metadata-Version: 1.0
Name: rbco.rename
Version: 0.2
Summary: A set of Python scripts to rename files in batch.
Home-page: UNKNOWN
Author: Rafael Oliveira
Author-email: rafaelbco@gmail.com
License: LGPL
Keywords: shell unix filesystem
Platform: UNKNOWN
Classifier: Programming Language :: Python
Classifier: Topic :: Software Development :: Libraries :: Python Modules
